MANIFEST.in
README.rst
setup.py
piupdue/ArduinoFlashEefc.py
piupdue/ArduinoFlashHardValues.py
piupdue/ArduinoFlashSerial.py
piupdue/ArduinoFlashXmodem.py
piupdue/Logger.py
piupdue/__init__.py
piupdue/piupdue.py
piupdue.egg-info/PKG-INFO
piupdue.egg-info/SOURCES.txt
piupdue.egg-info/dependency_links.txt
piupdue.egg-info/top_level.txt