Metadata-Version: 1.0
Name: piupdue
Version: 1.0.1
Summary: Upload code to Arduino Due from Python.
Home-page: https://github.com/johngrantuk/piupdue
Author: John Grant
Author-email: johngrantuk@googlemail.com
License: MIT
Platform: UNKNOWN
